Workbook

Sheet Player Statements
A1: PLAYER STATEMENTS
A3: INCOME STATEMENT | B3: 2024 | C3: 2025 | E3: BALANCE SHEET | F3: 2024 | G3: 2025 | I3: CASH FLOW STATEMENT | J3: 2024 | K3: 2025
A4: Revenue | B4: ='Fictional Co'!C4 -> 56 | C4: ='Fictional Co'!D4 -> 222 | E4: Cash and cash equivalents | F4: ='Fictional Co'!G4 -> 2949 | G4: ='Fictional Co'!H4 -> 42 | I4: Net loss | J4: ='Fictional Co'!K4 -> -4490 | K4: ='Fictional Co'!L4 -> -4875
A5: Cost of revenues | B5: ='Fictional Co'!C5 -> 300 | C5: ='Fictional Co'!D5 -> 552 | E5: Inventory | F5: ='Fictional Co'!G9 -> 110 | G5: ='Fictional Co'!H9 -> 250 | I5: Non-cash adjustments | J5: =SUM('Fictional Co'!K5:K8) -> 893 | K5: =SUM('Fictional Co'!L5:L8) -> 935
A6: Gross profit / (loss) | B6: =B4-B5 -> -244 | C6: =C4-C5 -> -330 | E6: Other current assets | F6: ='Fictional Co'!G10-'Fictional Co'!G4-'Fictional Co'!G9 -> 2481 | G6: ='Fictional Co'!H10-'Fictional Co'!H4-'Fictional Co'!H9 -> 561 | I6: Working-capital changes | J6: =SUM('Fictional Co'!K9:K11) -> -112 | K6: =SUM('Fictional Co'!L9:L11) -> -258
A7: R&D and sales spending | B7: =SUM('Fictional Co'!C7:C8) -> 2150 | C7: =SUM('Fictional Co'!D7:D8) -> 2600 | E7: Total current assets | F7: =SUM(F4:F6) -> 5540 | G7: =SUM(G4:G6) -> 853 | I7: Net cash from / (used in) operations | J7: =SUM(J4:J6) -> -3709 | K7: =SUM(K4:K6) -> -4198
A8: Other operating expenses, net | B8: ='Fictional Co'!C9-'Fictional Co'!C10 -> 1993 | C8: ='Fictional Co'!D9-'Fictional Co'!D10 -> 1637 | E8: Non-current assets | F8: ='Fictional Co'!G14 -> 2408 | G8: ='Fictional Co'!H14 -> 2522 | I8: Capital expenditure | J8: ='Fictional Co'!K16 -> -500 | K8: ='Fictional Co'!L16 -> -650
A9: Operating profit / (loss) | B9: =B6-B7-B8 -> -4387 | C9: =C6-C7-C8 -> -4567 | E9: Total assets | F9: =F7+F8 -> 7948 | G9: =G7+G8 -> 3375 | I9: Other investing cash flows | J9: ='Fictional Co'!K18-'Fictional Co'!K16 -> 1497 | K9: ='Fictional Co'!L18-'Fictional Co'!L16 -> 1936
A10: Net finance cost | B10: ='Fictional Co'!C12-'Fictional Co'!C13 -> 103 | C10: ='Fictional Co'!D12-'Fictional Co'!D13 -> 232 | E10: Current liabilities | F10: ='Fictional Co'!G21 -> 604 | G10: ='Fictional Co'!H21 -> 545 | I10: Net cash from investing | J10: =SUM(J8:J9) -> 997 | K10: =SUM(K8:K9) -> 1286
A11: Income tax expense | B11: ='Fictional Co'!C15 -> 0 | C11: ='Fictional Co'!D15 -> 76 | E11: Non-current liabilities | F11: ='Fictional Co'!G24 -> 5790 | G11: ='Fictional Co'!H24 -> 6036 | I11: Net cash from financing | J11: ='Fictional Co'!K22 -> 1650 | K11: ='Fictional Co'!L22 -> 5
A12: Net profit / (loss) | B12: =B9-B10-B11 -> -4490 | C12: =C9-C10-C11 -> -4875 | E12: Total liabilities | F12: =SUM(F10:F11) -> 6394 | G12: =SUM(G10:G11) -> 6581 | I12: Net change in cash | J12: =SUM(J7,J10,J11) -> -1062 | K12: =SUM(K7,K10,K11) -> -2907
E13: Total equity | F13: ='Fictional Co'!G28 -> 1554 | G13: ='Fictional Co'!H28 -> -3206 | I13: Opening cash | J13: ='Fictional Co'!K25 -> 4011 | K13: ='Fictional Co'!L25 -> 2949
E14: Total liabilities and equity | F14: =SUM(F12:F13) -> 7948 | G14: =SUM(G12:G13) -> 3375 | I14: Closing cash | J14: =J13+J12 -> 2949 | K14: =K13+K12 -> 42

Sheet Sheet1
C2: 2024 | D2: 2025 | G2: 2024 | H2: 2025 | K2: 2024 | L2: 2025
B3: INCOME STATEMENT | F3: BALANCE SHEET | J3: CASH FLOW STATEMENT
B4: Revenue | C4: 56 | D4: 222 | F4: Cash and cash equivalents | G4: =K26 -> 3356 | H4: =L26 -> 1725 | J4: Net loss | K4: =C16 -> -4561 | L4: =D16 -> -4343
B5: Cost of revenues | C5: 635 | D5: 602 | F5: Restricted deposits, current | G5: 357 | H5: 421 | J5: Depreciation | K5: 429 | L5: 425
B6: Gross profit / (loss) | C6: =C4-C5 -> -579 | D6: =D4-D5 -> -380 | F6: Short-term deposits | G6: 2000 | H6: 0 | J6: Non-cash note interest | K6: 396 | L6: 395
B7: Research and development, net | C7: 1256 | D7: 1060 | F7: Trade receivables | G7: 12 | H7: 52 | J7: Right-of-use and lease changes, net | K7: -64 | L7: 5
B8: Sales and marketing | C8: 630 | D8: 958 | F8: Other receivables | G8: 112 | H8: 88 | J8: Share-based compensation | K8: 132 | L8: 110
B9: General and administrative | C9: 2076 | D9: 1774 | F9: Inventory | G9: 72 | H9: 99 | J9: Change in trade and other receivables | K9: -23 | L9: =SUM(G7:G8)-SUM(H7:H8) -> -16
B10: Other income | C10: 83 | D10: 137 | F10: Total current assets | G10: =SUM(G4:G9) -> 5909 | H10: =SUM(H4:H9) -> 2385 | J10: Change in inventory | K10: -72 | L10: =G9-H9 -> -27
B11: Operating profit / (loss) | C11: =C6-SUM(C7:C9)+C10 -> -4458 | D11: =D6-SUM(D7:D9)+D10 -> -4035 | F11: Restricted deposits, non-current | G11: 58 | H11: 66 | J11: Change in operating payables | K11: 21 | L11: =SUM(H17:H18,H20)-SUM(G17:G18,G20) -> -102
B12: Finance expense | C12: 405 | D12: 405 | F12: Right-of-use assets | G12: 322 | H12: 211 | J12: Net cash from / (used in) operations | K12: =SUM(K4:K11) -> -3742 | L12: =SUM(L4:L11) -> -3553
B13: Finance income | C13: 302 | D13: 173 | F13: Property and equipment, net | G13: =K31-K16-K5-K32 -> 1588 | H13: =L31-L16-L5-L32 -> 1174
B14: Profit / (loss) before tax | C14: =C11-C12+C13 -> -4561 | D14: =D11-D12+D13 -> -4267 | F14: Total non-current assets | G14: =SUM(G11:G13) -> 1968 | H14: =SUM(H11:H13) -> 1451 | J14: Restricted deposit cash flows | K14: -6 | L14: =SUM(G5,G11)-SUM(H5,H11) -> -72
B15: Income tax expense | C15: 0 | D15: 76 | F15: Total assets | G15: =G10+G14 -> 7877 | H15: =H10+H14 -> 3836 | J15: Short-term deposit release | K15: 1503 | L15: =G6-H6 -> 2000
B16: Net profit / (loss) | C16: =C14-C15 -> -4561 | D16: =D14-D15 -> -4343 | J16: Acquisition of fixed assets | K16: -60 | L16: -19
F17: Trade payables | G17: 146 | H17: 99 | J17: Equipment sale proceeds | K17: 0 | L17: 8
F18: Employee payables | G18: 256 | H18: 164 | J18: Net cash from investing | K18: =SUM(K14:K17) -> 1437 | L18: =SUM(L14:L17) -> 1917
F19: Operating lease liability, current | G19: 169 | H19: 212
F20: Other payables | G20: 33 | H20: 70 | J20: Convertible note issuance proceeds | K20: 1650 | L20: 0
F21: Total current liabilities | G21: =SUM(G17:G20) -> 604 | H21: =SUM(H17:H20) -> 545 | J21: Option exercise proceeds | K21: 0 | L21: 5
F22: Operating lease liability, non-current | G22: 438 | H22: 289 | J22: Net cash from financing | K22: =SUM(K20:K21) -> 1650 | L22: =SUM(L20:L21) -> 5
F23: Convertible notes including accrued interest | G23: 5352 | H23: 5747
F24: Total non-current liabilities | G24: =SUM(G22:G23) -> 5790 | H24: =SUM(H22:H23) -> 6036 | J24: Net change in cash | K24: =SUM(K12,K18,K22) -> -655 | L24: =SUM(L12,L18,L22) -> -1631
F25: Total liabilities | G25: =G21+G24 -> 6394 | H25: =H21+H24 -> 6581 | J25: Opening cash | K25: 4011 | L25: =G4 -> 3356
F26: Paid-in capital at reporting precision | G26: =K29+K8+K21 -> 14669 | H26: =L29+L8+L21 -> 14784 | J26: Closing cash | K26: =K25+K24 -> 3356 | L26: =L25+L24 -> 1725
F27: Accumulated deficit | G27: =K30+K4 -> -13186 | H27: =L30+L4 -> -17529
F28: Total equity | G28: =G26+G27 -> 1483 | H28: =H26+H27 -> -2745
F29: Total liabilities and equity | G29: =G25+G28 -> 7877 | H29: =H25+H28 -> 3836 | J29: Opening paid-in capital | K29: 14537 | L29: =G26 -> 14669
J30: Opening accumulated deficit | K30: -8625 | L30: =G27 -> -13186
J31: Opening net property and equipment | K31: 1957 | L31: =G13 -> 1588
J32: Net book value of disposals | K32: 0 | L32: 8

Sheet Fictional Co
B1: FICTIONAL SCENARIO
C2: 2024 | D2: 2025 | G2: 2024 | H2: 2025 | K2: 2024 | L2: 2025
B3: INCOME STATEMENT | F3: BALANCE SHEET | J3: CASH FLOW STATEMENT
B4: Revenue | C4: 56 | D4: 222 | F4: Cash and cash equivalents | G4: =K26 -> 2949 | H4: =L26 -> 42 | J4: Net loss | K4: =C16 -> -4490 | L4: =D16 -> -4875
B5: Cost of revenues | C5: 300 | D5: 552 | F5: Restricted deposits, current | G5: 357 | H5: 421 | J5: Depreciation | K5: 429 | L5: 425
B6: Gross profit / (loss) | C6: =C4-C5 -> -244 | D6: =D4-D5 -> -330 | F6: Short-term deposits | G6: 2000 | H6: 0 | J6: Non-cash note interest | K6: 396 | L6: 395
B7: Research and development, net | C7: 1400 | D7: 1450 | F7: Trade receivables | G7: 12 | H7: 52 | J7: Right-of-use and lease changes, net | K7: -64 | L7: 5
B8: Sales and marketing | C8: 750 | D8: 1150 | F8: Other receivables | G8: 112 | H8: 88 | J8: Share-based compensation | K8: 132 | L8: 110
B9: General and administrative | C9: 2076 | D9: 1774 | F9: Inventory | G9: 110 | H9: 250 | J9: Change in trade and other receivables | K9: -23 | L9: =SUM(G7:G8)-SUM(H7:H8) -> -16
B10: Other income | C10: 83 | D10: 137 | F10: Total current assets | G10: =SUM(G4:G9) -> 5540 | H10: =SUM(H4:H9) -> 853 | J10: Change in inventory | K10: =-G9 -> -110 | L10: =G9-H9 -> -140
B11: Operating profit / (loss) | C11: =C6-SUM(C7:C9)+C10 -> -4387 | D11: =D6-SUM(D7:D9)+D10 -> -4567 | F11: Restricted deposits, non-current | G11: 58 | H11: 66 | J11: Change in operating payables | K11: 21 | L11: =SUM(H17:H18,H20)-SUM(G17:G18,G20) -> -102
B12: Finance expense | C12: 405 | D12: 405 | F12: Right-of-use assets | G12: 322 | H12: 211 | J12: Net cash from / (used in) operations | K12: =SUM(K4:K11) -> -3709 | L12: =SUM(L4:L11) -> -4198
B13: Finance income | C13: 302 | D13: 173 | F13: Property and equipment, net | G13: =K31-K16-K5-K32 -> 2028 | H13: =L31-L16-L5-L32 -> 2245
B14: Profit / (loss) before tax | C14: =C11-C12+C13 -> -4490 | D14: =D11-D12+D13 -> -4799 | F14: Total non-current assets | G14: =SUM(G11:G13) -> 2408 | H14: =SUM(H11:H13) -> 2522 | J14: Restricted deposit cash flows | K14: -6 | L14: =SUM(G5,G11)-SUM(H5,H11) -> -72
B15: Income tax expense | C15: 0 | D15: 76 | F15: Total assets | G15: =G10+G14 -> 7948 | H15: =H10+H14 -> 3375 | J15: Short-term deposit release | K15: 1503 | L15: =G6-H6 -> 2000
B16: Net profit / (loss) | C16: =C14-C15 -> -4490 | D16: =D14-D15 -> -4875 | J16: Acquisition of fixed assets | K16: -500 | L16: -650
F17: Trade payables | G17: 146 | H17: 99 | J17: Equipment sale proceeds | K17: 0 | L17: 8
F18: Employee payables | G18: 256 | H18: 164 | J18: Net cash from investing | K18: =SUM(K14:K17) -> 997 | L18: =SUM(L14:L17) -> 1286
F19: Operating lease liability, current | G19: 169 | H19: 212
B20: #Changelog | F20: Other payables | G20: 33 | H20: 70 | J20: Convertible note issuance proceeds | K20: 1650 | L20: 0
B21: Cost of revenues adjusted to reflect weak gross margins | F21: Total current liabilities | G21: =SUM(G17:G20) -> 604 | H21: =SUM(H17:H20) -> 545 | J21: Option exercise proceeds | K21: 0 | L21: 5
B22: R&D and sales spending increased to support expansion | F22: Operating lease liability, non-current | G22: 438 | H22: 289 | J22: Net cash from financing | K22: =SUM(K20:K21) -> 1650 | L22: =SUM(L20:L21) -> 5
B23: Inventory investment increased ahead of growth | F23: Convertible notes including accrued interest | G23: 5352 | H23: 5747
B24: Capital expenditure increased, intensifying cash burn | F24: Total non-current liabilities | G24: =SUM(G22:G23) -> 5790 | H24: =SUM(H22:H23) -> 6036 | J24: Net change in cash | K24: =SUM(K12,K18,K22) -> -1062 | L24: =SUM(L12,L18,L22) -> -2907
F25: Total liabilities | G25: =G21+G24 -> 6394 | H25: =H21+H24 -> 6581 | J25: Opening cash | K25: 4011 | L25: =G4 -> 2949
F26: Paid-in capital at reporting precision | G26: =K29+K8+K21 -> 14669 | H26: =L29+L8+L21 -> 14784 | J26: Closing cash | K26: =K25+K24 -> 2949 | L26: =L25+L24 -> 42
F27: Accumulated deficit | G27: =K30+K4 -> -13115 | H27: =L30+L4 -> -17990
F28: Total equity | G28: =G26+G27 -> 1554 | H28: =H26+H27 -> -3206
F29: Total liabilities and equity | G29: =G25+G28 -> 7948 | H29: =H25+H28 -> 3375 | J29: Opening paid-in capital | K29: 14537 | L29: =G26 -> 14669
J30: Opening accumulated deficit | K30: -8625 | L30: =G27 -> -13115
J31: Opening net property and equipment | K31: 1957 | L31: =G13 -> 2028
J32: Net book value of disposals | K32: 0 | L32: 8

Sheet Source Co
B2: Reported item | C2: 2024 | D2: 2025 | G2: 2024 | H2: 2025 | K2: 2024 | L2: 2025
B3: INCOME STATEMENT | F3: BALANCE SHEET | J3: CASH FLOW STATEMENT
B4: Revenue | C4: 56 | D4: 222 | F4: Cash and cash equivalents | G4: 3356 | H4: 1725 | J4: Net loss | K4: -4561 | L4: -4343
B5: Cost of revenues | C5: 635 | D5: 602 | F5: Restricted deposits, current | G5: 357 | H5: 421 | J5: Depreciation | K5: 429 | L5: 425
B6: Gross profit / (loss) | C6: -579 | D6: -380 | F6: Short-term deposits | G6: 2000 | H6: 0 | J6: Non-cash note interest | K6: 396 | L6: 395
B7: Research and development, net | C7: 1256 | D7: 1060 | F7: Trade receivables | G7: 12 | H7: 52 | J7: Right-of-use and lease changes, net | K7: -64 | L7: 5
B8: Sales and marketing | C8: 630 | D8: 958 | F8: Other receivables | G8: 112 | H8: 88 | J8: Share-based compensation | K8: 132 | L8: 110
B9: General and administrative | C9: 2076 | D9: 1774 | F9: Inventory | G9: 72 | H9: 99 | J9: Change in trade and other receivables | K9: -23 | L9: -16
B10: Other income | C10: 83 | D10: 137 | F10: Total current assets | G10: 5909 | H10: 2385 | J10: Change in inventory | K10: -72 | L10: -27
B11: Operating profit / (loss) | C11: -4458 | D11: -4035 | F11: Restricted deposits, non-current | G11: 58 | H11: 66 | J11: Change in operating payables | K11: 21 | L11: -102
B12: Finance expense | C12: 405 | D12: 405 | F12: Right-of-use assets | G12: 322 | H12: 211 | J12: Net cash from / (used in) operations | K12: -3742 | L12: -3553
B13: Finance income | C13: 302 | D13: 173 | F13: Property and equipment, net | G13: 1588 | H13: 1174
B14: Profit / (loss) before tax | C14: -4561 | D14: -4267 | F14: Total non-current assets | G14: 1968 | H14: 1451 | J14: Restricted deposit cash flows | K14: -6 | L14: -72
B15: Income tax expense | C15: 0 | D15: 76 | F15: Total assets | G15: 7877 | H15: 3836 | J15: Short-term deposit release | K15: 1503 | L15: 2000
B16: Net profit / (loss) | C16: -4561 | D16: -4343 | J16: Acquisition of fixed assets | K16: -60 | L16: -19
F17: Trade payables | G17: 146 | H17: 99 | J17: Equipment sale proceeds | K17: 0 | L17: 8
F18: Employee payables | G18: 256 | H18: 164 | J18: Net cash from investing | K18: 1437 | L18: 1917
F19: Operating lease liability, current | G19: 169 | H19: 212
F20: Other payables | G20: 33 | H20: 70 | J20: Convertible note issuance proceeds | K20: 1650 | L20: 0
F21: Total current liabilities | G21: 604 | H21: 545 | J21: Option exercise proceeds | K21: 0 | L21: 5
F22: Operating lease liability, non-current | G22: 438 | H22: 289 | J22: Net cash from financing | K22: 1650 | L22: 5
F23: Convertible notes including accrued interest | G23: 5352 | H23: 5747
F24: Total non-current liabilities | G24: 5790 | H24: 6036 | J24: Net change in cash | K24: -655 | L24: -1631
F25: Total liabilities | G25: 6394 | H25: 6581 | J25: Opening cash | K25: 4011 | L25: 3356
F26: Paid-in capital at reporting precision | G26: 14669 | H26: 14784 | J26: Closing cash | K26: 3356 | L26: 1725
F27: Accumulated deficit | G27: -13186 | H27: -17529
F28: Total equity | G28: 1483 | H28: -2745
F29: Total liabilities and equity | G29: 7877 | H29: 3836 | J29: Opening paid-in capital | K29: 14537 | L29: 14669
J30: Opening accumulated deficit | K30: -8625 | L30: -13186
J31: Opening net property and equipment | K31: 1957 | L31: 1588
J32: Net book value of disposals | K32: 0 | L32: 8
